requirements.txt
solida/APPNAME
solida/VERSION
solida/__init__.py
solida/__main__.py
solida/ansible_wrapper.py
solida/cache_manager.py
solida/config_manager.py
solida/pipelines_manager.py
solida/cli/__init__.py
solida/cli/info.py
solida/cli/refresh.py
solida/cli/setup.py
solida/config/config.yaml
solida/playbooks/common.yaml
solida/playbooks/install_gatk_pipeline.yaml
solida/playbooks/install_pipeline.yaml
solida/playbooks/replace_paths.yaml
solida/playbooks/snakemake_wrappers.yaml
solida/playbooks/templates/notify.smk.j2
solida/playbooks/templates/run.project.j2
solida/playbooks/vars/gatk.yaml
solida/playbooks/vars/main.yaml
solida-0.9.7.2.dist-info/LICENSE
solida-0.9.7.2.dist-info/METADATA
solida-0.9.7.2.dist-info/WHEEL
solida-0.9.7.2.dist-info/entry_points.txt
solida-0.9.7.2.dist-info/top_level.txt
solida-0.9.7.2.dist-info/RECORD
