Metadata-Version: 2.1
Name: solida
Version: 0.9.7.2
Summary: NGS pipelines bootstrapper
Home-page: https://github.com/solida-core/solida
Author: Gianmauro Cuccuru
Author-email: gmauro@gmail.com
License: GPLv3
Keywords: NGS,pipeline deployment,bioinformatics
Platform: UNKNOWN
Classifier: Development Status :: 4 - Beta
Classifier: Environment :: Console
Classifier: Intended Audience :: Developers
Classifier: Intended Audience :: Science/Research
Classifier: Programming Language :: Python :: 3.7
Classifier: Programming Language :: Python :: 3.8
Classifier: Programming Language :: Python :: 3.9
Classifier: License :: OSI Approved :: GNU General Public License v3 (GPLv3)
Classifier: Topic :: Scientific/Engineering :: Bio-Informatics
Requires-Dist: ansible (==2.7.16)
Requires-Dist: appdirs (==1.4.3)
Requires-Dist: comoda (==0.4.0)
Requires-Dist: gitpython (==2.1.10)
Requires-Dist: gitdb2 (==2.0.6)
